data_prep_kit_m_ashraf/__init__.py
data_prep_kit_m_ashraf/data_prep_kit.py
data_prep_kit_m_ashraf-0.0.1.dist-info/METADATA
data_prep_kit_m_ashraf-0.0.1.dist-info/WHEEL
data_prep_kit_m_ashraf-0.0.1.dist-info/licenses/LICENSE
data_prep_kit_m_ashraf-0.0.1.dist-info/RECORD
